mkf/__init__.py
mkf/__main__.py
mkf-0.3.0.dist-info/licenses/LICENSE
mkf-0.3.0.dist-info/METADATA
mkf-0.3.0.dist-info/WHEEL
mkf-0.3.0.dist-info/entry_points.txt
mkf-0.3.0.dist-info/top_level.txt
mkf-0.3.0.dist-info/RECORD
