Metadata-Version: 2.4
Name: mkf
Version: 0.3.0
Summary: A simple CLI tool to generate FastAPI starter projects with a modular structure.
License-Expression: MIT
Project-URL: Homepage, https://github.com/4nddrs/mkf
Project-URL: Repository, https://github.com/4nddrs/mkf
Project-URL: Issues, https://github.com/4nddrs/mkf/issues
Classifier: Development Status :: 3 - Alpha
Classifier: Intended Audience :: Developers
Classifier: Programming Language :: Python :: 3
Classifier: Programming Language :: Python :: 3.6
Classifier: Programming Language :: Python :: 3.7
Classifier: Programming Language :: Python :: 3.8
Classifier: Programming Language :: Python :: 3.9
Classifier: Programming Language :: Python :: 3.10
Classifier: Programming Language :: Python :: 3.11
Requires-Python: >=3.6
License-File: LICENSE
Dynamic: license-file
